README.rst
setup.cfg
setup.py
DFOGN.egg-info/PKG-INFO
DFOGN.egg-info/SOURCES.txt
DFOGN.egg-info/dependency_links.txt
DFOGN.egg-info/requires.txt
DFOGN.egg-info/top_level.txt
DFOGN.egg-info/zip-safe
dfogn/__init__.py
dfogn/alternative_move.py
dfogn/dfogn.py
dfogn/dfogn_resampling.py
dfogn/linear_altmov.py
dfogn/trust_region.py
dfogn/util.py
dfogn/version.py