Metadata-Version: 1.1
Name: DFOGN
Version: 1.0.2
Summary: A simple derivative-free solver for (box constrained) nonlinear least-squares minimization
Home-page: https://github.com/numericalalgorithmsgroup/dfogn/
Author: Lindon Roberts
Author-email: lindon.roberts@maths.ox.ac.uk
License: GNU GPL
Download-URL: https://github.com/numericalalgorithmsgroup/dfogn/archive/v1.0.2.tar.gz
Keywords: mathematics derivative free optimization nonlinear least squares
Platform: UNKNOWN
Classifier: Development Status :: 5 - Production/Stable
Classifier: Environment :: Console
Classifier: Framework :: IPython
Classifier: Framework :: Jupyter
Classifier: Intended Audience :: Financial and Insurance Industry
Classifier: Intended Audience :: Science/Research
Classifier: License :: OSI Approved :: GNU General Public License (GPL)
Classifier: Operating System :: MacOS
Classifier: Operating System :: Microsoft :: Windows
Classifier: Operating System :: POSIX
Classifier: Operating System :: Unix
Classifier: Programming Language :: Python
Classifier: Programming Language :: Python :: 2
Classifier: Programming Language :: Python :: 3
Classifier: Topic :: Scientific/Engineering
Classifier: Topic :: Scientific/Engineering :: Mathematics
